mqtt_broker/__init__.py
mqtt_broker/broker.py
mqtt_broker-0.0.1.dist-info/LICENSE
mqtt_broker-0.0.1.dist-info/METADATA
mqtt_broker-0.0.1.dist-info/WHEEL
mqtt_broker-0.0.1.dist-info/top_level.txt
mqtt_broker-0.0.1.dist-info/RECORD
