Metadata-Version: 2.1
Name: mqtt_broker
Version: 0.0.1
Summary: A utility package to wrap an mqtt client creation
Author-email: Kim Baddeley <kim.baddeley@gmail.com>
Project-URL: Homepage, https://github.com/pypa/sampleproject
Project-URL: Issues, https://github.com/pypa/sampleproject/issues
Classifier: Programming Language :: Python :: 3
Classifier: License :: OSI Approved :: MIT License
Classifier: Operating System :: OS Independent
Requires-Python: >=3.8
License-File: LICENSE
Requires-Dist: python-dotenv>=1.0
Requires-Dist: paho.mqtt>=2.1
